tai_sql/__init__.py
tai_sql/cli/commands/__init__.py
tai_sql/cli/commands/cmd_deploy/__init__.py
tai_sql/cli/commands/cmd_deploy/config.py
tai_sql/cli/commands/cmd_deploy/local.py
tai_sql/cli/commands/cmd_deploy/main.py
tai_sql/cli/commands/cmd_deploy/workflow.py
tai_sql/cli/commands/cmd_generate/__init__.py
tai_sql/cli/commands/cmd_generate/funcs.py
tai_sql/cli/commands/cmd_generate/main.py
tai_sql/cli/commands/cmd_info/__init__.py
tai_sql/cli/commands/cmd_info/main.py
tai_sql/cli/commands/cmd_info/status.py
tai_sql/cli/commands/cmd_init/__init__.py
tai_sql/cli/commands/cmd_init/main.py
tai_sql/cli/commands/cmd_init/model.py
tai_sql/cli/commands/cmd_ping/__init__.py
tai_sql/cli/commands/cmd_ping/main.py
tai_sql/cli/commands/cmd_roles/__init__.py
tai_sql/cli/commands/cmd_roles/main.py
tai_sql/cli/commands/cmd_schema/__init__.py
tai_sql/cli/commands/cmd_schema/model.py
tai_sql/cli/commands/cmd_schema/new.py
tai_sql/cli/commands/cmd_schema/set_default.py
tai_sql/cli/commands/utils/__init__.py
tai_sql/cli/commands/utils/connectivity.py
tai_sql/cli/commands/utils/create.py
tai_sql/cli/commands/utils/github/__init__.py
tai_sql/cli/commands/utils/github/auth.py
tai_sql/cli/commands/utils/github/client.py
tai_sql/cli/commands/utils/github/models.py
tai_sql/cli/main.py
tai_sql/cli/services/__init__.py
tai_sql/cli/services/ddl.py
tai_sql/cli/services/drift.py
tai_sql/cli/services/keycloak.py
tai_sql/core/__init__.py
tai_sql/core/funcs.py
tai_sql/core/provider.py
tai_sql/drivers/__init__.py
tai_sql/drivers/base.py
tai_sql/drivers/mysql.py
tai_sql/drivers/postgresql.py
tai_sql/drivers/sqlserver.py
tai_sql/generators/__init__.py
tai_sql/generators/base.py
tai_sql/generators/crud/__init__.py
tai_sql/generators/crud/asyn/__init__.py
tai_sql/generators/crud/asyn/templates/__init__.py.jinja2
tai_sql/generators/crud/asyn/templates/daos.py.jinja2
tai_sql/generators/crud/asyn/templates/dtos.py.jinja2
tai_sql/generators/crud/asyn/templates/macros.jinja2
tai_sql-0.3.59.dist-info/METADATA
tai_sql-0.3.59.dist-info/WHEEL
tai_sql-0.3.59.dist-info/entry_points.txt
tai_sql-0.3.59.dist-info/licenses/LICENSE
tai_sql-0.3.59.dist-info/RECORD
