Metadata-Version: 2.4
Name: tai-sql
Version: 0.3.59
Summary: SQL database management and code generation tool
License: MIT
License-File: LICENSE
Keywords: sql,database,code-generation,orm,sqlalchemy
Author: MateoSaezMata
Author-email: msaez@triplealpha.in
Requires-Python: >=3.10,<4.0
Classifier: Development Status :: 4 - Beta
Classifier: Intended Audience :: Developers
Classifier: License :: OSI Approved :: MIT License
Classifier: Programming Language :: Python :: 3
Classifier: Programming Language :: Python :: 3.10
Classifier: Programming Language :: Python :: 3.11
Classifier: Programming Language :: Python :: 3.12
Classifier: Topic :: Database
Classifier: Topic :: Software Development :: Code Generators
Provides-Extra: optional
Requires-Dist: click (>=8.2.1,<9.0)
Requires-Dist: cryptography (>=45.0.4,<46.0)
Requires-Dist: graphviz (>=0.20.3,<1.0)
Requires-Dist: jinja2 (>=3.1.6,<4.0)
Requires-Dist: pandas (>=2.2.3,<3.0) ; extra == "optional"
Requires-Dist: psycopg2-binary (>=2.9.10,<3.0)
Requires-Dist: pydantic (>=2.11.7,<3.0)
Requires-Dist: pynacl (>=1.5.0,<2.0)
Requires-Dist: requests (>=2.32.4,<3.0)
Requires-Dist: rich (>=14.2.0,<15.0)
Requires-Dist: sqlalchemy (>=2.0.42,<3.0)
Requires-Dist: sqlparse (>=0.5.3,<1.0)
Requires-Dist: tai-alphi (>=2.0.1,<3.0)
Project-URL: Homepage, https://www.triplealpha.in/es/
Project-URL: Issues, https://github.com/triplealpha-innovation/tai-sql/issues
Project-URL: Repository, https://github.com/triplealpha-innovation/tai-sql
